LICENSE
README.md
setup.py
compensating_transaction/__init__.py
compensating_transaction/exceptions.py
compensating_transaction/transaction.py
compensating_transaction.egg-info/PKG-INFO
compensating_transaction.egg-info/SOURCES.txt
compensating_transaction.egg-info/dependency_links.txt
compensating_transaction.egg-info/top_level.txt