Metadata-Version: 2.1
Name: compensating-transaction
Version: 0.0.1
Summary: compensating transaction
Home-page: https://github.com/rubbish822/compensating-transaction
Author: rubbish
Author-email: rubbish@rubbish.com
License: MIT Licence
Keywords: pip,compensating-transaction,atomicity
Platform: any
License-File: LICENSE
